stdcpp/__init__.py
stdcpp-0.5.0.dist-info/METADATA
stdcpp-0.5.0.dist-info/WHEEL
stdcpp-0.5.0.dist-info/RECORD
