Metadata-Version: 2.1
Name: stdcpp
Version: 0.5.0
Summary: cout & cerr like in C++
Home-page: https://github.com/gergelyk/python-stdcpp
License: MIT
Author: Grzegorz Krason
Author-email: grzegorz.krason@gmail.com
Requires-Python: >=3.8,<4.0
Classifier: License :: OSI Approved :: MIT License
Classifier: Programming Language :: Python :: 3
Classifier: Programming Language :: Python :: 3.8
Classifier: Programming Language :: Python :: 3.9
Classifier: Programming Language :: Python :: 3.10
Classifier: Programming Language :: Python :: 3.11
Project-URL: Repository, https://github.com/gergelyk/python-stdcpp
